setup.py
pyfirebase/__init__.py
pyfirebase/decorators.py
pyfirebase/firebase.py
pyfirebase.egg-info/PKG-INFO
pyfirebase.egg-info/SOURCES.txt
pyfirebase.egg-info/dependency_links.txt
pyfirebase.egg-info/not-zip-safe
pyfirebase.egg-info/pbr.json
pyfirebase.egg-info/requires.txt
pyfirebase.egg-info/top_level.txt