Metadata-Version: 1.1
Name: pyfirebase
Version: 1.2
Summary: Firebase Python Plugin
Home-page: http://github.com/andela-cnnadi/pyfirebase
Author: Chidiebere Nnadi
Author-email: chidiebere.nnadi@gmail.com
License: MIT
Keywords: firebase python pyfirebase
Platform: UNKNOWN
Classifier: Environment :: Console
Classifier: Intended Audience :: Developers
Classifier: License :: OSI Approved :: MIT License
Classifier: Operating System :: OS Independent
Classifier: Programming Language :: Python :: 2.7
Classifier: Natural Language :: English
